pytosdr/__init__.py
pytosdr/pytosdr.py
pytosdr-1.0.2.dist-info/LICENSE
pytosdr-1.0.2.dist-info/METADATA
pytosdr-1.0.2.dist-info/WHEEL
pytosdr-1.0.2.dist-info/top_level.txt
pytosdr-1.0.2.dist-info/RECORD
